<schemalist>
	<schema id="com.github.lainsce.niu" path="/com/github/lainsce/niu/">
		<key name="window-x" type="i">
			<default>-1</default>
			<summary>Window position</summary>
			<description>The x axis of window position</description>
		</key>
		<key name="window-y" type="i">
			<default>-1</default>
			<summary>Window position</summary>
			<description>The y axis of window position</description>
		</key>
		<key type='b' name="indicator-state">
		  <default>false</default>
		  <summary>To show Indicator or not</summary>
		  <description>To show Indicator or not</description>
		</key>
		<key type='b' name="background-state">
		  <default>false</default>
		  <summary>To stay in background or not</summary>
		  <description>To stay in background or not</description>
		</key>
        <key type='b' name="pomodoro">
		  <default>false</default>
		  <summary>To have a Nataniev Pomodoro or not</summary>
		  <description>To have a Nataniev Pomodoro or not</description>
		</key>
		<key type='b' name="show-beats">
		  <default>true</default>
		  <summary>To show Beats or not</summary>
		  <description>To show Beats or not</description>
		</key>
	</schema>
</schemalist>
